{"nodes": [{"id": "brand_prigeex_wordmark", "label": "PrigeeX wordmark SVG (1200x240, viewBox 600x120) - horizontal lockup combining the square X-mark logo (left) with the full brand name 'PrigeeX' as bold text (font-weight 800, Inter/Manrope, letter-spacing -2.5) in near-white (#F4F6F5) with the 'X' character accent-colored in brand blue (#1670E8). Used for horizontal header placements, marketing banners, and contexts requiring the full brand name alongside the mark.", "file_type": "image", "source_file": "public/brand/prigeex-wordmark.svg", "source_location": null, "source_url": null, "captured_at": null, "author": null, "contributor": null}], "edges": [{"source": "brand_prigeex_wordmark", "target": "brand_prigeex_logo", "relation": "references", "confidence": "EXTRACTED", "confidence_score": 1.0, "source_file": "public/brand/prigeex-wordmark.svg", "source_location": "line 39-46", "weight": 1.0}, {"source": "brand_prigeex_wordmark", "target": "brand_prigeex_x_inline", "relation": "semantically_similar_to", "confidence": "INFERRED", "confidence_score": 0.85, "source_file": "public/brand/prigeex-wordmark.svg", "source_location": null, "weight": 0.8}], "hyperedges": [{"id": "prigeex_brand_system", "label": "PrigeeX brand identity system - all SVG and raster assets sharing the signature crossing-X motif, deep navy palette (#0B2A6B/#03102E), and brand blue (#1670E8), forming a coherent multi-format brand system covering favicon, inline mark, square logo, solid mark, wordmark lockup, and PNG export.", "nodes": ["brand_prigeex_favicon", "brand_prigeex_logo", "brand_prigeex_mark_solid", "brand_prigeex_x_inline", "brand_prigeex_wordmark", "public_prigeex_logo", "public_image"], "relation": "form", "confidence": "INFERRED", "confidence_score": 0.95, "source_file": "public/brand/prigeex-wordmark.svg"}]}